subclass_register/__init__.py
subclass_register/subclass_register.py
subclass_register-1.0.1.dist-info/LICENSE
subclass_register-1.0.1.dist-info/METADATA
subclass_register-1.0.1.dist-info/WHEEL
subclass_register-1.0.1.dist-info/top_level.txt
subclass_register-1.0.1.dist-info/RECORD
