Metadata-Version: 2.1
Name: subclass-register
Version: 1.0.1
Summary: Automatically log all new subclasses of a specified base class.
Home-page: UNKNOWN
Author: Yngve Mardal Moe
Author-email: yngve.m.moe@gmail.com
License: MIT
Platform: UNKNOWN
